bhmsh_collingwoodbh/__init__.py
bhmsh_collingwoodbh/__main__.py
bhmsh_collingwoodbh-0.0.9.dist-info/LICENSE
bhmsh_collingwoodbh-0.0.9.dist-info/METADATA
bhmsh_collingwoodbh-0.0.9.dist-info/WHEEL
bhmsh_collingwoodbh-0.0.9.dist-info/entry_points.txt
bhmsh_collingwoodbh-0.0.9.dist-info/top_level.txt
bhmsh_collingwoodbh-0.0.9.dist-info/RECORD
